Metadata-Version: 2.1
Name: instabotai
Version: 1.0.29
Summary: Instagram bot scripts for promotion and API python wrapper.
Home-page: https://github.com/instagrambot/instabotai
Author: Steffan Jensen
Author-email: 6hourapp@gmail.com
License: Apache Software License 2.0
Keywords: instagram,bot,api,wrapper
Platform: UNKNOWN
Classifier: Development Status :: 5 - Production/Stable
Classifier: Intended Audience :: Information Technology
Classifier: License :: OSI Approved :: Apache Software License
Classifier: Programming Language :: Python :: 3.4
Classifier: Programming Language :: Python :: 3.5
Classifier: Programming Language :: Python :: 3.6
Classifier: Programming Language :: Python :: 3.7
